finchvox/__init__.py
finchvox/__main__.py
finchvox/audio_utils.py
finchvox/cli.py
finchvox/conversation.py
finchvox/metrics.py
finchvox/processor.py
finchvox/server.py
finchvox/session.py
finchvox/telemetry.py
finchvox/ui_routes.py
finchvox/collector/__init__.py
finchvox/collector/__main__.py
finchvox/collector/audio_handler.py
finchvox/collector/collector_routes.py
finchvox/collector/config.py
finchvox/collector/log_service.py
finchvox/collector/log_writer.py
finchvox/collector/server.py
finchvox/collector/service.py
finchvox/collector/writer.py
finchvox/ui/session_detail.html
finchvox/ui/sessions_list.html
finchvox/ui/css/app.css
finchvox/ui/images/favicon.ico
finchvox/ui/images/finchvox-logo.png
finchvox/ui/js/conversation.js
finchvox/ui/js/logs_view.js
finchvox/ui/js/metrics_view.js
finchvox/ui/js/session_detail.js
finchvox/ui/js/sessions_list.js
finchvox/ui/js/time-utils.js
finchvox/ui/lib/alpine.min.js
finchvox/ui/lib/chart.min.js
finchvox/ui/lib/wavesurfer.min.js
finchvox-0.0.9.dist-info/METADATA
finchvox-0.0.9.dist-info/WHEEL
finchvox-0.0.9.dist-info/entry_points.txt
finchvox-0.0.9.dist-info/licenses/LICENSE
finchvox-0.0.9.dist-info/RECORD
