Metadata-Version: 2.4
Name: finchvox
Version: 0.0.9
Summary: Voice AI observability dev tool for Pipecat
License-Expression: MIT
License-File: LICENSE
Requires-Python: >=3.10
Requires-Dist: aiofiles>=24.1.0
Requires-Dist: aiohttp>=3.9.0
Requires-Dist: aiortc>=1.14.0
Requires-Dist: fastapi>=0.115.0
Requires-Dist: grpcio>=1.60.0
Requires-Dist: loguru>=0.7.0
Requires-Dist: opentelemetry-exporter-otlp-proto-grpc>=1.27.0
Requires-Dist: opentelemetry-instrumentation-logging>=0.48b0
Requires-Dist: opentelemetry-proto>=1.27.0
Requires-Dist: opentelemetry-sdk>=1.27.0
Requires-Dist: pipecat-ai[cartesia,daily,deepgram,silero]>=0.0.98
Requires-Dist: protobuf<6.0.0,>=4.25.0
Requires-Dist: python-multipart>=0.0.9
Requires-Dist: uvicorn[standard]>=0.32.0
Provides-Extra: dev
Requires-Dist: pytest-asyncio>=0.23.0; extra == 'dev'
Requires-Dist: pytest-cov>=4.0.0; extra == 'dev'
Requires-Dist: pytest>=7.0.0; extra == 'dev'
Requires-Dist: ruff>=0.14.10; extra == 'dev'
Requires-Dist: twine>=6.2.0; extra == 'dev'
